LICENSE
MANIFEST.in
README.rst
requirements-test-py26.txt
requirements-test-py32.txt
requirements-test.txt
setup.cfg
setup.py
callee/__init__.py
callee/_compat.py
callee/attributes.py
callee/base.py
callee/collections.py
callee/functions.py
callee/general.py
callee/numbers.py
callee/objects.py
callee/operators.py
callee/strings.py
callee/types.py
callee.egg-info/PKG-INFO
callee.egg-info/SOURCES.txt
callee.egg-info/dependency_links.txt
callee.egg-info/top_level.txt